pybrother/__init__.py
pybrother/__main__.py
pybrother/cli.py
pybrother-0.1.1.dist-info/METADATA
pybrother-0.1.1.dist-info/WHEEL
pybrother-0.1.1.dist-info/entry_points.txt
pybrother-0.1.1.dist-info/licenses/LICENSE
pybrother-0.1.1.dist-info/RECORD
