Metadata-Version: 2.4
Name: pybrother
Version: 0.1.1
Summary: Universal Brother Label Printer with PNG and labelprinterkit modes
Project-URL: Homepage, https://github.com/example/pybrother
Project-URL: Repository, https://github.com/example/pybrother.git
Project-URL: Issues, https://github.com/example/pybrother/issues
Author: Brother Label Printer Team
License: MIT License
License-File: LICENSE
Keywords: cli,label-printer,printing,pybrother,uvx
Classifier: Development Status :: 4 - Beta
Classifier: Intended Audience :: Developers
Classifier: License :: OSI Approved :: MIT License
Classifier: Programming Language :: Python :: 3
Classifier: Programming Language :: Python :: 3.8
Classifier: Programming Language :: Python :: 3.9
Classifier: Programming Language :: Python :: 3.10
Classifier: Programming Language :: Python :: 3.11
Classifier: Programming Language :: Python :: 3.12
Requires-Python: >=3.9
Requires-Dist: aiozeroconf>=0.1.8
Requires-Dist: inline-snapshot>=0.23.2
Requires-Dist: pillow<10.0.0,>=9.5.0
Requires-Dist: pyipp>=0.15.0
Requires-Dist: zeroconf>=0.147.0
Provides-Extra: dev
Requires-Dist: flake8>=6.0.0; extra == 'dev'
Requires-Dist: inline-snapshot>=0.12.0; extra == 'dev'
Requires-Dist: isort>=5.12.0; extra == 'dev'
Requires-Dist: labelprinterkit>=0.6.0; extra == 'dev'
Requires-Dist: mypy>=1.0.0; extra == 'dev'
Requires-Dist: pytest-asyncio>=0.21.0; extra == 'dev'
Requires-Dist: pytest>=7.0.0; extra == 'dev'
Requires-Dist: zeroconf>=0.47.0; extra == 'dev'
Provides-Extra: discovery
Requires-Dist: zeroconf>=0.47.0; extra == 'discovery'
Provides-Extra: labelprinterkit
Requires-Dist: labelprinterkit>=0.6.0; extra == 'labelprinterkit'
Provides-Extra: test
Requires-Dist: inline-snapshot>=0.12.0; extra == 'test'
Requires-Dist: pytest-asyncio>=0.21.0; extra == 'test'
Requires-Dist: pytest>=7.0.0; extra == 'test'
